.travis.yml
LICENSE
MANIFEST.in
README.rst
setup.cfg
setup.py
tox.ini
Mopidy_Transistor.egg-info/PKG-INFO
Mopidy_Transistor.egg-info/SOURCES.txt
Mopidy_Transistor.egg-info/dependency_links.txt
Mopidy_Transistor.egg-info/entry_points.txt
Mopidy_Transistor.egg-info/not-zip-safe
Mopidy_Transistor.egg-info/requires.txt
Mopidy_Transistor.egg-info/top_level.txt
mopidy_transistor/__init__.py
mopidy_transistor/backend.py
mopidy_transistor/ext.conf
mopidy_transistor/frontend.py
mopidy_transistor/interface.py
mopidy_transistor/library.py
mopidy_transistor/utils.py
mopidy_transistor/protocol/TransistorMasterRouter.py
mopidy_transistor/protocol/TransistorMsg.py
mopidy_transistor/protocol/TransistorSlaveRouter.py
mopidy_transistor/protocol/__init__.py
mopidy_transistor/web/__init__.py
mopidy_transistor/web/alarms.py
mopidy_transistor/web/basics.py
mopidy_transistor/web/event_source.py
mopidy_transistor/web/settings.py
mopidy_transistor/web/settings_conf.py
mopidy_transistor/web/transistor.py
mopidy_transistor/web/site/about.html
mopidy_transistor/web/site/alarms.html
mopidy_transistor/web/site/base.html
mopidy_transistor/web/site/browse.html
mopidy_transistor/web/site/calibration.html
mopidy_transistor/web/site/index.html
mopidy_transistor/web/site/login.html
mopidy_transistor/web/site/podcasts.html
mopidy_transistor/web/site/radios.html
mopidy_transistor/web/site/settings.html
mopidy_transistor/web/site/update.html
mopidy_transistor/web/site/wifi.html
mopidy_transistor/web/site/css/battery.css
mopidy_transistor/web/site/css/config.css
mopidy_transistor/web/site/css/popup.css
mopidy_transistor/web/site/css/style.css
mopidy_transistor/web/site/css/transistor.css
mopidy_transistor/web/site/css/tuner.css
mopidy_transistor/web/site/images/logo.png
mopidy_transistor/web/site/images/radio.png
mopidy_transistor/web/site/js/browse.js
mopidy_transistor/web/site/js/calibration.js
mopidy_transistor/web/site/js/index.js
mopidy_transistor/web/site/js/podcasts.js
mopidy_transistor/web/site/js/radios.js
mopidy_transistor/web/site/js/settings.js
mopidy_transistor/web/site/js/transistor.js
mopidy_transistor/web/site/js/update.js
mopidy_transistor/web/site/js/wifi.js
mopidy_transistor/web/site/vendor/fontawesome/css/all.css
