Metadata-Version: 2.1
Name: Mopidy-Transistor
Version: 0.2.0
Summary: Mopidy Extension for Transistor Radios
Home-page: https://github.com/lukh/mopidy-transistor
Author: Vivien Henry
Author-email: vivien.henry@outlook.fr
License: Apache License, Version 2.0
Platform: UNKNOWN
Classifier: Environment :: No Input/Output (Daemon)
Classifier: Intended Audience :: End Users/Desktop
Classifier: License :: OSI Approved :: Apache Software License
Classifier: Operating System :: OS Independent
Classifier: Programming Language :: Python :: 3
Classifier: Programming Language :: Python :: 3.7
Classifier: Programming Language :: Python :: 3.8
Classifier: Topic :: Multimedia :: Sound/Audio :: Players
Requires-Python: >=3.7
Provides-Extra: lint
Provides-Extra: release
Provides-Extra: test
Provides-Extra: dev
